{
    "KEY_AV_FORWARD_MOVE": {
        "name": "dav_spinner_forward_backward",
        "type": "AXIS_CHANGE",
        "value": "POSITIVE"
    },
    "KEY_AV_BACK_MOVE": {
        "name": "dav_spinner_forward_backward",
        "type": "AXIS_CHANGE",
        "value": "NEGATIVE"
    },
    "KEY_AV_RIGHT_MOVE": {
        "name": "dav_spinner_left_right",
        "type": "AXIS_CHANGE",
        "value": "POSITIVE"
    },
    "KEY_AV_LEFT_MOVE": {
        "name": "dav_spinner_left_right",
        "type": "AXIS_CHANGE",
        "value": "NEGATIVE"
    },
    "KEY_AV_UP_MOVE": {
        "name": "dav_spinner_up",
        "type": "AXIS_CHANGE",
        "value": "POSITIVE"
    },
    "KEY_AV_DOWN_MOVE": {
        "name": "dav_spinner_down",
        "type": "AXIS_CHANGE",
        "value": "POSITIVE"
    },
    "KEY_WORLD_ENTER_AV": {
        "name": "dav_get_on",
        "type": "BUTTON_PRESSED",
        "value": "POSITIVE"
    },
    "KEY_AV_EXIT_AV": {
        "name": "dav_get_off",
        "type": "BUTTON_HOLD_PROGRESS",
        "value": "POSITIVE"
    },
    "KEY_AV_CAMERA": {
        "name": "dav_change_view",
        "type": "BUTTON_PRESSED",
        "value": "POSITIVE"
    },
    "KEY_AV_TOGGLE_DOOR_1": {
        "name": "dav_toggle_door_1",
        "type": "BUTTON_PRESSED",
        "value": "POSITIVE"
    },
    "KEY_AV_TOGGLE_AUTO_PILOT": {
        "name": "dav_toggle_auto_pilot",
        "type": "BUTTON_PRESSED",
        "value": "POSITIVE"
    },
    "KEY_WORLD_SELECT_UPPER_CHOICE": {
        "name": "ChoiceScrollUp",
        "type": "BUTTON_PRESSED",
        "value": "POSITIVE"
    },
    "KEY_WORLD_SELECT_LOWER_CHOICE": {
        "name": "ChoiceScrollDown",
        "type": "BUTTON_PRESSED",
        "value": "POSITIVE"
    },
    "KEY_AV_TOGGLE_RADIO": {
        "name": "dpad_up",
        "type": "BUTTON_RELEASED",
        "value": "ZERO"
    },
    "KEY_AV_OPEN_RADIO_POPUP": {
        "name": "dav_operate_radio",
        "type": "BUTTON_HOLD_COMPLETE",
        "value": "POSITIVE"
    }
}