{"autopilot_speed_level":2,"is_autopilot_info_panel":true,"flight_mode":"Spinner","garage_info_list":[{"model_index":1,"is_purchased":false,"type_index":1,"name":"Vehicle.av_rayfield_excalibur_dav"},{"model_index":2,"is_purchased":false,"type_index":1,"name":"Vehicle.av_militech_manticore_dav"},{"model_index":3,"is_purchased":false,"type_index":1,"name":"Vehicle.av_zetatech_atlus_dav"},{"model_index":4,"is_purchased":false,"type_index":1,"name":"Vehicle.av_zetatech_surveyor_dav"},{"model_index":5,"is_purchased":false,"type_index":1,"name":"Vehicle.q000_nomad_border_patrol_heli_dav"}],"is_free_summon_mode":true,"heli_horizenal_boost_ratio":2,"is_disable_spinner_roll_tilt":false,"is_enable_community_spawn":true,"spawn_frequency":2,"is_mute_all":false,"is_mute_flight":false,"language_index":1,"version":"1.5.1","is_unit_km_per_hour":false,"mappin_history":[],"favorite_location_list":[{"pos":{"x":0,"z":0,"y":0},"name":"Unselected","is_selected":true},{"pos":{"x":0,"z":0,"y":0},"name":"Not Registered","is_selected":false},{"pos":{"x":0,"z":0,"y":0},"name":"Not Registered","is_selected":false},{"pos":{"x":0,"z":0,"y":0},"name":"Not Registered","is_selected":false},{"pos":{"x":0,"z":0,"y":0},"name":"Not Registered","is_selected":false},{"pos":{"x":0,"z":0,"y":0},"name":"Not Registered","is_selected":false}],"model_index_in_free":1,"model_type_index_in_free":1}